hdytto/__init__.py
hdytto/codec.py
hdytto/comment.py
hdytto/const.py
hdytto/dowhile.py
hdytto/increment.py
hdytto/util.py
hdytto-0.2.1.dist-info/LICENSE
hdytto-0.2.1.dist-info/METADATA
hdytto-0.2.1.dist-info/WHEEL
hdytto-0.2.1.dist-info/top_level.txt
hdytto-0.2.1.dist-info/RECORD
