Metadata-Version: 2.1
Name: hdytto
Version: 0.2.1
Summary: Add not pythonic syntax into your python.
Home-page: https://github.com/TRSasasusu/hdytto
Author: kaito kishi
Author-email: trsasasusu@gmail.com
License: MIT
Keywords: shell commands alias
Platform: UNKNOWN
Classifier: Programming Language :: Python :: 3.8
Classifier: License :: OSI Approved :: MIT License
Requires-Python: >=3.8
License-File: LICENSE
